clidow/__init__.py
clidow/data.py
clidow/download.py
clidow-0.0.2.dist-info/LICENSE
clidow-0.0.2.dist-info/METADATA
clidow-0.0.2.dist-info/WHEEL
clidow-0.0.2.dist-info/top_level.txt
clidow-0.0.2.dist-info/RECORD
